{"title":"Transmission Towers","description":"Transmission tower locations","count":7,"type":"FeatureCollection","features":[{"type":"Feature","properties":{"id":"TT-001","index":1,"name":"Tower 1","power":"tower","osm_id":"12726547500"},"geometry":{"type":"Point","coordinates":[85.082309,25.651504]}},{"type":"Feature","properties":{"id":"TT-002","index":2,"name":"Tower 2","power":"tower","osm_id":"12726593301"},"geometry":{"type":"Point","coordinates":[85.08139,25.65759]}},{"type":"Feature","properties":{"id":"TT-003","index":3,"name":"Tower 3","power":"tower","osm_id":"12726593302"},"geometry":{"type":"Point","coordinates":[85.080175,25.660489]}},{"type":"Feature","properties":{"id":"TT-004","index":4,"name":"Tower 4","power":"tower","osm_id":"12726593303"},"geometry":{"type":"Point","coordinates":[85.075954,25.663439]}},{"type":"Feature","properties":{"id":"TT-005","index":5,"name":"Tower 5","power":"tower","osm_id":"12726593304"},"geometry":{"type":"Point","coordinates":[85.072026,25.666396]}},{"type":"Feature","properties":{"id":"TT-006","index":6,"name":"Tower 6","power":"tower","osm_id":"12726593305"},"geometry":{"type":"Point","coordinates":[85.068283,25.669491]}},{"type":"Feature","properties":{"id":"TT-007","index":7,"name":"Tower 7","power":"tower","osm_id":"12726593306"},"geometry":{"type":"Point","coordinates":[85.065618,25.673215]}}]}